buckshot_roulette/__init__.py
buckshot_roulette/ai.py
buckshot_roulette/game.py
buckshot_roulette-0.1.1.dist-info/LICENSE
buckshot_roulette-0.1.1.dist-info/METADATA
buckshot_roulette-0.1.1.dist-info/WHEEL
buckshot_roulette-0.1.1.dist-info/top_level.txt
buckshot_roulette-0.1.1.dist-info/RECORD
