Metadata-Version: 2.1
Name: buckshot-roulette
Version: 0.1.1
Summary: Buckshot Roulette library for python, with complete game features & reasonable efficiency.
Author: Bytestorm
Project-URL: Homepage, https://github.com/Bytestorm5/Buckshot-Roulette-Python
Project-URL: Issues, https://github.com/Bytestorm5/Buckshot-Roulette-Python/issues
Classifier: Programming Language :: Python :: 3
Classifier: License :: OSI Approved :: MIT License
Classifier: Operating System :: OS Independent
Requires-Python: >=3.11
License-File: LICENSE
